AUTHORS.rst
CONTRIBUTING.rst
HISTORY.rst
LICENSE
MANIFEST.in
README.rst
setup.cfg
setup.py
docs/Makefile
docs/authors.rst
docs/conf.py
docs/contributing.rst
docs/history.rst
docs/index.rst
docs/installation.rst
docs/make.bat
docs/readme.rst
docs/receiveoneip.py
docs/sample.py
docs/sendoneip.py
docs/usage.rst
mcastsocket/__init__.py
mcastsocket/mcastsocket.py
mcastsocket.egg-info/PKG-INFO
mcastsocket.egg-info/SOURCES.txt
mcastsocket.egg-info/dependency_links.txt
mcastsocket.egg-info/not-zip-safe
mcastsocket.egg-info/top_level.txt
tests/__init__.py
tests/test_mcastsocket.py