Metadata-Version: 1.1
Name: mcastsocket
Version: 1.0.1
Summary: Provides a simple interface for configuring multicast socket services
Home-page: https://github.com/mcfletch/mcastsocket
Author: Mike C. Fletcher
Author-email: mcfletch@vrplumber.com
License: LGPL
Keywords: mcastsocket
Platform: UNKNOWN
Classifier: Development Status :: 2 - Pre-Alpha
Classifier: Intended Audience :: Developers
Classifier: License :: OSI Approved :: GNU Lesser General Public License v2 (LGPLv2)
Classifier: Natural Language :: English
Classifier: Programming Language :: Python :: 2.7
Classifier: Programming Language :: Python :: 3
Classifier: Programming Language :: Python :: 3.3
Classifier: Programming Language :: Python :: 3.4
Classifier: Programming Language :: Python :: 3.5
